graphs_asaqib1/_init_.py
graphs_asaqib1/bfs.py
graphs_asaqib1/heapq.py
graphs_asaqib1/sp.py
asaqib1-0.0.9.dist-info/METADATA
asaqib1-0.0.9.dist-info/WHEEL
asaqib1-0.0.9.dist-info/RECORD
