Metadata-Version: 2.4
Name: asaqib1
Version: 0.0.9
Summary: A small homework assignment to navigate through creating a python library
Project-URL: Homepage, https://github.com/pypa/sampleproject
Project-URL: Bug Tracker, https://github.com/pypa/sampleproject/issues
Author-email: Alizah Saqib <asaqib@msudenver.edu>
Classifier: License :: OSI Approved :: MIT License
Classifier: Operating System :: OS Independent
Classifier: Programming Language :: Python :: 3
Requires-Python: >=3.7
